VERILOG/dff.v
module dff(clk, D, Q);
    input clk, D;
    output Q;
    wire clk_bar, M, O, P, N, X_bar, Q_bar, X;
    not (clk_bar, clk);
    nand (M, clk_bar, D);
    nand (N, clk_bar, ~D);
    nand (X, M, X_bar);
    nand (X_bar, N, X);
    nand (O, clk, X);
    nand (P, clk, X_bar);
    nand (Q, O, Q_bar);
    nand (Q_bar, P, Q);

endmodule

vlsi_project/2023102027_Project/VERILOG/dff_testbench.v
module dff_tb;
    reg clk;
    reg D;
    wire Q;

    dff uut (
        .clk(clk),
        .D(D),
        .Q(Q)
    );

    initial begin
        clk = 0;
        forever #10 clk = ~clk;
    end

    initial begin
        D = 0;
        #15 D = 1;
        #20 D = 0;
        #30 D = 1;
        #40 D = 0;
        #50 $finish;
    end

    initial begin
        $dumpfile("dff_tb.vcd"); 
        $dumpvars(0, dff_tb);   
        $monitor("Time=%0t | clk=%b | D=%b | Q=%b ", $time, clk, D, Q);
    end

endmodule

VERILOG/dff_tb.vcd
$date
	Sun Dec  1 00:29:39 2024
$end
$version
	Icarus Verilog
$end
$timescale
	1s
$end
$scope module dff_tb $end
$var wire 1 ! Q $end
$var reg 1 " D $end
$var reg 1 # clk $end
$scope module uut $end
$var wire 1 " D $end
$var wire 1 $ M $end
$var wire 1 % N $end
$var wire 1 & O $end
$var wire 1 ' P $end
$var wire 1 ! Q $end
$var wire 1 ( Q_bar $end
$var wire 1 ) X $end
$var wire 1 * X_bar $end
$var wire 1 # clk $end
$var wire 1 + clk_bar $end
$upscope $end
$upscope $end
$enddefinitions $end
#0
$dumpvars
1+
1*
0)
x(
1'
1&
0%
1$
0#
0"
x!
$end
#10
0!
1%
1(
0+
0'
1#
#15
1"
#20
0*
1)
0$
1+
1'
0#
#30
0(
1$
1!
0+
0&
1#
#35
0"
#40
0)
1*
0%
1+
1&
0#
#50
0!
1%
1(
0+
0'
1#
#60
0%
1+
1'
0#
#65
0*
1)
1%
0$
1"
#70
0(
1$
1!
0+
0&
1#
#80
0$
1+
1&
0#
#90
1$
0+
0&
1#
#100
0$
1+
1&
0#
#105
0)
1*
0%
1$
0"
#110
0!
1%
1(
0+
0'
1#
#120
0%
1+
1'
0#
#130
1%
0+
0'
1#
#140
0%
1+
1'
0#
#150
1%
0+
0'
1#
