VERILOG/pgblock.v
`timescale 1ns / 1ps
module xor_gate(
    input a, b,
    output xor_out
);
    wire n1, n2, n3;
    nand(n1, a, b);
    nand(n2, a, n1);
    nand(n3, b, n1);
    nand(xor_out, n2, n3);
endmodule
module and_gate(
    input a, b,
    output and_out
);
    wire n1;
    nand(n1, a, b);
    nand(and_out, n1, n1);
endmodule
module pggen( a,b,p,g);
  
  input a;
  input b;
  output p;
  output g;

and_gate a1(a,b,g);
xor_gate x1(a,b,p);


endmodule

module pgblock (
    input a1, a2, a3, a4,
    input b1, b2, b3, b4,
    output p1, p2, p3, p4,
    output g1, g2, g3, g4
);
    pggen pg1(a1, b1, p1, g1);
    pggen pg2(a2, b2, p2, g2);
    pggen pg3(a3, b3, p3, g3);
    pggen pg4(a4, b4, p4, g4);
    
endmodule

vlsi_project/2023102027_Project/VERILOG/pg_testbench.v
`timescale 1ns / 1ps

module pg_testbench;

    reg a1, a2, a3, a4;
    reg b1, b2, b3, b4;
    wire p1, p2, p3, p4;
    wire g1, g2, g3, g4;

    pgblock uut (
        .a1(a1), .a2(a2), .a3(a3), .a4(a4),
        .b1(b1), .b2(b2), .b3(b3), .b4(b4),
        .p1(p1), .p2(p2), .p3(p3), .p4(p4),
        .g1(g1), .g2(g2), .g3(g3), .g4(g4)
    );

    integer i;

    initial begin
        $display("Testing pgblock with all combinations of a1 and b1");
        $dumpfile("pg.vcd"); 
        $dumpvars(0, pg_testbench);
        for (i = 0; i < 256; i = i + 1) begin
            {a1, a2, a3, a4, b1, b2, b3, b4} = i;
            #10;
            $display("Test Case %d: a1=%b a2=%b a3=%b a4=%b, b1=%b b2=%b b3=%b b4=%b     p1=%b p2=%b p3=%b p4=%b, g1=%b g2=%b g3=%b g4=%b", 
                    i, a1, a2, a3, a4, b1, b2, b3, b4, p1, p2, p3, p4, g1, g2, g3, g4);
        end

        $finish;
    end

endmodule

VERILOG/pg.vcd
$date
	Sun Dec  1 00:09:18 2024
$end
$version
	Icarus Verilog
$end
$timescale
	1ps
$end
$scope module pg_testbench $end
$var wire 1 ! p4 $end
$var wire 1 " p3 $end
$var wire 1 # p2 $end
$var wire 1 $ p1 $end
$var wire 1 % g4 $end
$var wire 1 & g3 $end
$var wire 1 ' g2 $end
$var wire 1 ( g1 $end
$var reg 1 ) a1 $end
$var reg 1 * a2 $end
$var reg 1 + a3 $end
$var reg 1 , a4 $end
$var reg 1 - b1 $end
$var reg 1 . b2 $end
$var reg 1 / b3 $end
$var reg 1 0 b4 $end
$var integer 32 1 i [31:0] $end
$scope module uut $end
$var wire 1 ) a1 $end
$var wire 1 * a2 $end
$var wire 1 + a3 $end
$var wire 1 , a4 $end
$var wire 1 - b1 $end
$var wire 1 . b2 $end
$var wire 1 / b3 $end
$var wire 1 0 b4 $end
$var wire 1 ! p4 $end
$var wire 1 " p3 $end
$var wire 1 # p2 $end
$var wire 1 $ p1 $end
$var wire 1 % g4 $end
$var wire 1 & g3 $end
$var wire 1 ' g2 $end
$var wire 1 ( g1 $end
$scope module pg1 $end
$var wire 1 ) a $end
$var wire 1 - b $end
$var wire 1 $ p $end
$var wire 1 ( g $end
$scope module a1 $end
$var wire 1 ) a $end
$var wire 1 ( and_out $end
$var wire 1 - b $end
$var wire 1 2 n1 $end
$upscope $end
$scope module x1 $end
$var wire 1 ) a $end
$var wire 1 - b $end
$var wire 1 3 n1 $end
$var wire 1 4 n2 $end
$var wire 1 5 n3 $end
$var wire 1 $ xor_out $end
$upscope $end
$upscope $end
$scope module pg2 $end
$var wire 1 * a $end
$var wire 1 . b $end
$var wire 1 # p $end
$var wire 1 ' g $end
$scope module a1 $end
$var wire 1 * a $end
$var wire 1 ' and_out $end
$var wire 1 . b $end
$var wire 1 6 n1 $end
$upscope $end
$scope module x1 $end
$var wire 1 * a $end
$var wire 1 . b $end
$var wire 1 7 n1 $end
$var wire 1 8 n2 $end
$var wire 1 9 n3 $end
$var wire 1 # xor_out $end
$upscope $end
$upscope $end
$scope module pg3 $end
$var wire 1 + a $end
$var wire 1 / b $end
$var wire 1 " p $end
$var wire 1 & g $end
$scope module a1 $end
$var wire 1 + a $end
$var wire 1 & and_out $end
$var wire 1 / b $end
$var wire 1 : n1 $end
$upscope $end
$scope module x1 $end
$var wire 1 + a $end
$var wire 1 / b $end
$var wire 1 ; n1 $end
$var wire 1 < n2 $end
$var wire 1 = n3 $end
$var wire 1 " xor_out $end
$upscope $end
$upscope $end
$scope module pg4 $end
$var wire 1 , a $end
$var wire 1 0 b $end
$var wire 1 ! p $end
$var wire 1 % g $end
$scope module a1 $end
$var wire 1 , a $end
$var wire 1 % and_out $end
$var wire 1 0 b $end
$var wire 1 > n1 $end
$upscope $end
$scope module x1 $end
$var wire 1 , a $end
$var wire 1 0 b $end
$var wire 1 ? n1 $end
$var wire 1 @ n2 $end
$var wire 1 A n3 $end
$var wire 1 ! xor_out $end
$upscope $end
$upscope $end
$upscope $end
$upscope $end
$enddefinitions $end
#0
$dumpvars
1A
1@
1?
1>
1=
1<
1;
1:
19
18
17
16
15
14
13
12
b0 1
00
0/
0.
0-
0,
0+
0*
0)
0(
0'
0&
0%
0$
0#
0"
0!
$end
#10000
1!
0A
10
b1 1
#20000
1"
0!
0=
1A
1/
00
b10 1
#30000
1!
0A
10
b11 1
#40000
1#
0"
0!
09
1=
1A
1.
0/
00
b100 1
#50000
1!
0A
10
b101 1
#60000
1"
0!
0=
1A
1/
00
b110 1
#70000
1!
0A
10
b111 1
#80000
1$
0#
0"
0!
05
19
1=
1A
1-
0.
0/
00
b1000 1
#90000
1!
0A
10
b1001 1
#100000
1"
0!
0=
1A
1/
00
b1010 1
#110000
1!
0A
10
b1011 1
#120000
1#
0"
0!
09
1=
1A
1.
0/
00
b1100 1
#130000
1!
0A
10
b1101 1
#140000
1"
0!
0=
1A
1/
00
b1110 1
#150000
1!
0A
10
b1111 1
#160000
0$
0#
0"
0@
15
19
1=
1A
1,
0-
0.
0/
00
b10000 1
#170000
0!
1%
1@
0>
0?
1A
10
b10001 1
#180000
1!
1"
0%
0@
0=
1>
1?
1/
00
b10010 1
#190000
0!
1%
1@
0>
0?
1A
10
b10011 1
#200000
1!
1#
0"
0%
0@
09
1=
1>
1?
1.
0/
00
b10100 1
#210000
0!
1%
1@
0>
0?
1A
10
b10101 1
#220000
1!
1"
0%
0@
0=
1>
1?
1/
00
b10110 1
#230000
0!
1%
1@
0>
0?
1A
10
b10111 1
#240000
1!
1$
0#
0"
0%
0@
05
19
1=
1>
1?
1-
0.
0/
00
b11000 1
#250000
0!
1%
1@
0>
0?
1A
10
b11001 1
#260000
1!
1"
0%
0@
0=
1>
1?
1/
00
b11010 1
#270000
0!
1%
1@
0>
0?
1A
10
b11011 1
#280000
1!
1#
0"
0%
0@
09
1=
1>
1?
1.
0/
00
b11100 1
#290000
0!
1%
1@
0>
0?
1A
10
b11101 1
#300000
1!
1"
0%
0@
0=
1>
1?
1/
00
b11110 1
#310000
0!
1%
1@
0>
0?
1A
10
b11111 1
#320000
0$
0#
0%
0<
15
19
1=
1>
1?
1+
0,
0-
0.
0/
00
b100000 1
#330000
1!
0A
10
b100001 1
#340000
0"
1&
1<
0!
0:
0;
1=
1A
1/
00
b100010 1
#350000
1!
0A
10
b100011 1
#360000
1"
1#
0&
0<
0!
09
1:
1;
1A
1.
0/
00
b100100 1
#370000
1!
0A
10
b100101 1
#380000
0"
1&
1<
0!
0:
0;
1=
1A
1/
00
b100110 1
#390000
1!
0A
10
b100111 1
#400000
1"
1$
0#
0&
0<
0!
05
19
1:
1;
1A
1-
0.
0/
00
b101000 1
#410000
1!
0A
10
b101001 1
#420000
0"
1&
1<
0!
0:
0;
1=
1A
1/
00
b101010 1
#430000
1!
0A
10
b101011 1
#440000
1"
1#
0&
0<
0!
09
1:
1;
1A
1.
0/
00
b101100 1
#450000
1!
0A
10
b101101 1
#460000
0"
1&
1<
0!
0:
0;
1=
1A
1/
00
b101110 1
#470000
1!
0A
10
b101111 1
#480000
1"
0$
0#
0&
0<
0@
15
19
1:
1;
1A
1,
0-
0.
0/
00
b110000 1
#490000
0!
1%
1@
0>
0?
1A
10
b110001 1
#500000
0"
1!
1&
1<
0%
0@
0:
0;
1=
1>
1?
1/
00
b110010 1
#510000
0!
1%
1@
0>
0?
1A
10
b110011 1
#520000
1"
1!
1#
0&
0<
0%
0@
09
1:
1;
1>
1?
1.
0/
00
b110100 1
#530000
0!
1%
1@
0>
0?
1A
10
b110101 1
#540000
0"
1!
1&
1<
0%
0@
0:
0;
1=
1>
1?
1/
00
b110110 1
#550000
0!
1%
1@
0>
0?
1A
10
b110111 1
#560000
1"
1!
1$
0#
0&
0<
0%
0@
05
19
1:
1;
1>
1?
1-
0.
0/
00
b111000 1
#570000
0!
1%
1@
0>
0?
1A
10
b111001 1
#580000
0"
1!
1&
1<
0%
0@
0:
0;
1=
1>
1?
1/
00
b111010 1
#590000
0!
1%
1@
0>
0?
1A
10
b111011 1
#600000
1"
1!
1#
0&
0<
0%
0@
09
1:
1;
1>
1?
1.
0/
00
b111100 1
#610000
0!
1%
1@
0>
0?
1A
10
b111101 1
#620000
0"
1!
1&
1<
0%
0@
0:
0;
1=
1>
1?
1/
00
b111110 1
#630000
0!
1%
1@
0>
0?
1A
10
b111111 1
#640000
0$
0&
0%
08
15
19
1:
1;
1>
1?
1*
0+
0,
0-
0.
0/
00
b1000000 1
#650000
1!
0A
10
b1000001 1
#660000
1"
0!
0=
1A
1/
00
b1000010 1
#670000
1!
0A
10
b1000011 1
#680000
0#
1'
18
0"
0!
06
07
19
1=
1A
1.
0/
00
b1000100 1
#690000
1!
0A
10
b1000101 1
#700000
1"
0!
0=
1A
1/
00
b1000110 1
#710000
1!
0A
10
b1000111 1
#720000
1#
1$
0'
08
0"
0!
05
16
17
1=
1A
1-
0.
0/
00
b1001000 1
#730000
1!
0A
10
b1001001 1
#740000
1"
0!
0=
1A
1/
00
b1001010 1
#750000
1!
0A
10
b1001011 1
#760000
0#
1'
18
0"
0!
06
07
19
1=
1A
1.
0/
00
b1001100 1
#770000
1!
0A
10
b1001101 1
#780000
1"
0!
0=
1A
1/
00
b1001110 1
#790000
1!
0A
10
b1001111 1
#800000
1#
0$
0'
08
0"
0@
15
16
17
1=
1A
1,
0-
0.
0/
00
b1010000 1
#810000
0!
1%
1@
0>
0?
1A
10
b1010001 1
#820000
1!
1"
0%
0@
0=
1>
1?
1/
00
b1010010 1
#830000
0!
1%
1@
0>
0?
1A
10
b1010011 1
#840000
0#
1!
1'
18
0"
0%
0@
06
07
19
1=
1>
1?
1.
0/
00
b1010100 1
#850000
0!
1%
1@
0>
0?
1A
10
b1010101 1
#860000
1!
1"
0%
0@
0=
1>
1?
1/
00
b1010110 1
#870000
0!
1%
1@
0>
0?
1A
10
b1010111 1
#880000
1#
1!
1$
0'
08
0"
0%
0@
05
16
17
1=
1>
1?
1-
0.
0/
00
b1011000 1
#890000
0!
1%
1@
0>
0?
1A
10
b1011001 1
#900000
1!
1"
0%
0@
0=
1>
1?
1/
00
b1011010 1
#910000
0!
1%
1@
0>
0?
1A
10
b1011011 1
#920000
0#
1!
1'
18
0"
0%
0@
06
07
19
1=
1>
1?
1.
0/
00
b1011100 1
#930000
0!
1%
1@
0>
0?
1A
10
b1011101 1
#940000
1!
1"
0%
0@
0=
1>
1?
1/
00
b1011110 1
#950000
0!
1%
1@
0>
0?
1A
10
b1011111 1
#960000
1#
0$
0'
08
0%
0<
15
16
17
1=
1>
1?
1+
0,
0-
0.
0/
00
b1100000 1
#970000
1!
0A
10
b1100001 1
#980000
0"
1&
1<
0!
0:
0;
1=
1A
1/
00
b1100010 1
#990000
1!
0A
10
b1100011 1
#1000000
0#
1"
1'
18
0&
0<
0!
06
07
19
1:
1;
1A
1.
0/
00
b1100100 1
#1010000
1!
0A
10
b1100101 1
#1020000
0"
1&
1<
0!
0:
0;
1=
1A
1/
00
b1100110 1
#1030000
1!
0A
10
b1100111 1
#1040000
1#
1"
1$
0'
08
0&
0<
0!
05
16
17
1:
1;
1A
1-
0.
0/
00
b1101000 1
#1050000
1!
0A
10
b1101001 1
#1060000
0"
1&
1<
0!
0:
0;
1=
1A
1/
00
b1101010 1
#1070000
1!
0A
10
b1101011 1
#1080000
0#
1"
1'
18
0&
0<
0!
06
07
19
1:
1;
1A
1.
0/
00
b1101100 1
#1090000
1!
0A
10
b1101101 1
#1100000
0"
1&
1<
0!
0:
0;
1=
1A
1/
00
b1101110 1
#1110000
1!
0A
10
b1101111 1
#1120000
1#
1"
0$
0'
08
0&
0<
0@
15
16
17
1:
1;
1A
1,
0-
0.
0/
00
b1110000 1
#1130000
0!
1%
1@
0>
0?
1A
10
b1110001 1
#1140000
0"
1!
1&
1<
0%
0@
0:
0;
1=
1>
1?
1/
00
b1110010 1
#1150000
0!
1%
1@
0>
0?
1A
10
b1110011 1
#1160000
0#
1"
1!
1'
18
0&
0<
0%
0@
06
07
19
1:
1;
1>
1?
1.
0/
00
b1110100 1
#1170000
0!
1%
1@
0>
0?
1A
10
b1110101 1
#1180000
0"
1!
1&
1<
0%
0@
0:
0;
1=
1>
1?
1/
00
b1110110 1
#1190000
0!
1%
1@
0>
0?
1A
10
b1110111 1
#1200000
1#
1"
1!
1$
0'
08
0&
0<
0%
0@
05
16
17
1:
1;
1>
1?
1-
0.
0/
00
b1111000 1
#1210000
0!
1%
1@
0>
0?
1A
10
b1111001 1
#1220000
0"
1!
1&
1<
0%
0@
0:
0;
1=
1>
1?
1/
00
b1111010 1
#1230000
0!
1%
1@
0>
0?
1A
10
b1111011 1
#1240000
0#
1"
1!
1'
18
0&
0<
0%
0@
06
07
19
1:
1;
1>
1?
1.
0/
00
b1111100 1
#1250000
0!
1%
1@
0>
0?
1A
10
b1111101 1
#1260000
0"
1!
1&
1<
0%
0@
0:
0;
1=
1>
1?
1/
00
b1111110 1
#1270000
0!
1%
1@
0>
0?
1A
10
b1111111 1
#1280000
0'
0&
0%
04
15
16
17
1:
1;
1>
1?
1)
0*
0+
0,
0-
0.
0/
00
b10000000 1
#1290000
1!
0A
10
b10000001 1
#1300000
1"
0!
0=
1A
1/
00
b10000010 1
#1310000
1!
0A
10
b10000011 1
#1320000
1#
0"
0!
09
1=
1A
1.
0/
00
b10000100 1
#1330000
1!
0A
10
b10000101 1
#1340000
1"
0!
0=
1A
1/
00
b10000110 1
#1350000
1!
0A
10
b10000111 1
#1360000
0$
1(
14
0#
0"
0!
02
03
15
19
1=
1A
1-
0.
0/
00
b10001000 1
#1370000
1!
0A
10
b10001001 1
#1380000
1"
0!
0=
1A
1/
00
b10001010 1
#1390000
1!
0A
10
b10001011 1
#1400000
1#
0"
0!
09
1=
1A
1.
0/
00
b10001100 1
#1410000
1!
0A
10
b10001101 1
#1420000
1"
0!
0=
1A
1/
00
b10001110 1
#1430000
1!
0A
10
b10001111 1
#1440000
1$
0(
04
0#
0"
0@
12
13
19
1=
1A
1,
0-
0.
0/
00
b10010000 1
#1450000
0!
1%
1@
0>
0?
1A
10
b10010001 1
#1460000
1!
1"
0%
0@
0=
1>
1?
1/
00
b10010010 1
#1470000
0!
1%
1@
0>
0?
1A
10
b10010011 1
#1480000
1!
1#
0"
0%
0@
09
1=
1>
1?
1.
0/
00
b10010100 1
#1490000
0!
1%
1@
0>
0?
1A
10
b10010101 1
#1500000
1!
1"
0%
0@
0=
1>
1?
1/
00
b10010110 1
#1510000
0!
1%
1@
0>
0?
1A
10
b10010111 1
#1520000
0$
1!
1(
14
0#
0"
0%
0@
02
03
15
19
1=
1>
1?
1-
0.
0/
00
b10011000 1
#1530000
0!
1%
1@
0>
0?
1A
10
b10011001 1
#1540000
1!
1"
0%
0@
0=
1>
1?
1/
00
b10011010 1
#1550000
0!
1%
1@
0>
0?
1A
10
b10011011 1
#1560000
1!
1#
0"
0%
0@
09
1=
1>
1?
1.
0/
00
b10011100 1
#1570000
0!
1%
1@
0>
0?
1A
10
b10011101 1
#1580000
1!
1"
0%
0@
0=
1>
1?
1/
00
b10011110 1
#1590000
0!
1%
1@
0>
0?
1A
10
b10011111 1
#1600000
1$
0(
04
0#
0%
0<
12
13
19
1=
1>
1?
1+
0,
0-
0.
0/
00
b10100000 1
#1610000
1!
0A
10
b10100001 1
#1620000
0"
1&
1<
0!
0:
0;
1=
1A
1/
00
b10100010 1
#1630000
1!
0A
10
b10100011 1
#1640000
1"
1#
0&
0<
0!
09
1:
1;
1A
1.
0/
00
b10100100 1
#1650000
1!
0A
10
b10100101 1
#1660000
0"
1&
1<
0!
0:
0;
1=
1A
1/
00
b10100110 1
#1670000
1!
0A
10
b10100111 1
#1680000
0$
1"
1(
14
0#
0&
0<
0!
02
03
15
19
1:
1;
1A
1-
0.
0/
00
b10101000 1
#1690000
1!
0A
10
b10101001 1
#1700000
0"
1&
1<
0!
0:
0;
1=
1A
1/
00
b10101010 1
#1710000
1!
0A
10
b10101011 1
#1720000
1"
1#
0&
0<
0!
09
1:
1;
1A
1.
0/
00
b10101100 1
#1730000
1!
0A
10
b10101101 1
#1740000
0"
1&
1<
0!
0:
0;
1=
1A
1/
00
b10101110 1
#1750000
1!
0A
10
b10101111 1
#1760000
1$
1"
0(
04
0#
0&
0<
0@
12
13
19
1:
1;
1A
1,
0-
0.
0/
00
b10110000 1
#1770000
0!
1%
1@
0>
0?
1A
10
b10110001 1
#1780000
0"
1!
1&
1<
0%
0@
0:
0;
1=
1>
1?
1/
00
b10110010 1
#1790000
0!
1%
1@
0>
0?
1A
10
b10110011 1
#1800000
1"
1!
1#
0&
0<
0%
0@
09
1:
1;
1>
1?
1.
0/
00
b10110100 1
#1810000
0!
1%
1@
0>
0?
1A
10
b10110101 1
#1820000
0"
1!
1&
1<
0%
0@
0:
0;
1=
1>
1?
1/
00
b10110110 1
#1830000
0!
1%
1@
0>
0?
1A
10
b10110111 1
#1840000
0$
1"
1!
1(
14
0#
0&
0<
0%
0@
02
03
15
19
1:
1;
1>
1?
1-
0.
0/
00
b10111000 1
#1850000
0!
1%
1@
0>
0?
1A
10
b10111001 1
#1860000
0"
1!
1&
1<
0%
0@
0:
0;
1=
1>
1?
1/
00
b10111010 1
#1870000
0!
1%
1@
0>
0?
1A
10
b10111011 1
#1880000
1"
1!
1#
0&
0<
0%
0@
09
1:
1;
1>
1?
1.
0/
00
b10111100 1
#1890000
0!
1%
1@
0>
0?
1A
10
b10111101 1
#1900000
0"
1!
1&
1<
0%
0@
0:
0;
1=
1>
1?
1/
00
b10111110 1
#1910000
0!
1%
1@
0>
0?
1A
10
b10111111 1
#1920000
1$
0(
04
0&
0%
08
12
13
19
1:
1;
1>
1?
1*
0+
0,
0-
0.
0/
00
b11000000 1
#1930000
1!
0A
10
b11000001 1
#1940000
1"
0!
0=
1A
1/
00
b11000010 1
#1950000
1!
0A
10
b11000011 1
#1960000
0#
1'
18
0"
0!
06
07
19
1=
1A
1.
0/
00
b11000100 1
#1970000
1!
0A
10
b11000101 1
#1980000
1"
0!
0=
1A
1/
00
b11000110 1
#1990000
1!
0A
10
b11000111 1
#2000000
0$
1#
1(
14
0'
08
0"
0!
02
03
15
16
17
1=
1A
1-
0.
0/
00
b11001000 1
#2010000
1!
0A
10
b11001001 1
#2020000
1"
0!
0=
1A
1/
00
b11001010 1
#2030000
1!
0A
10
b11001011 1
#2040000
0#
1'
18
0"
0!
06
07
19
1=
1A
1.
0/
00
b11001100 1
#2050000
1!
0A
10
b11001101 1
#2060000
1"
0!
0=
1A
1/
00
b11001110 1
#2070000
1!
0A
10
b11001111 1
#2080000
1$
1#
0(
04
0'
08
0"
0@
12
13
16
17
1=
1A
1,
0-
0.
0/
00
b11010000 1
#2090000
0!
1%
1@
0>
0?
1A
10
b11010001 1
#2100000
1!
1"
0%
0@
0=
1>
1?
1/
00
b11010010 1
#2110000
0!
1%
1@
0>
0?
1A
10
b11010011 1
#2120000
0#
1!
1'
18
0"
0%
0@
06
07
19
1=
1>
1?
1.
0/
00
b11010100 1
#2130000
0!
1%
1@
0>
0?
1A
10
b11010101 1
#2140000
1!
1"
0%
0@
0=
1>
1?
1/
00
b11010110 1
#2150000
0!
1%
1@
0>
0?
1A
10
b11010111 1
#2160000
0$
1#
1!
1(
14
0'
08
0"
0%
0@
02
03
15
16
17
1=
1>
1?
1-
0.
0/
00
b11011000 1
#2170000
0!
1%
1@
0>
0?
1A
10
b11011001 1
#2180000
1!
1"
0%
0@
0=
1>
1?
1/
00
b11011010 1
#2190000
0!
1%
1@
0>
0?
1A
10
b11011011 1
#2200000
0#
1!
1'
18
0"
0%
0@
06
07
19
1=
1>
1?
1.
0/
00
b11011100 1
#2210000
0!
1%
1@
0>
0?
1A
10
b11011101 1
#2220000
1!
1"
0%
0@
0=
1>
1?
1/
00
b11011110 1
#2230000
0!
1%
1@
0>
0?
1A
10
b11011111 1
#2240000
1$
1#
0(
04
0'
08
0%
0<
12
13
16
17
1=
1>
1?
1+
0,
0-
0.
0/
00
b11100000 1
#2250000
1!
0A
10
b11100001 1
#2260000
0"
1&
1<
0!
0:
0;
1=
1A
1/
00
b11100010 1
#2270000
1!
0A
10
b11100011 1
#2280000
0#
1"
1'
18
0&
0<
0!
06
07
19
1:
1;
1A
1.
0/
00
b11100100 1
#2290000
1!
0A
10
b11100101 1
#2300000
0"
1&
1<
0!
0:
0;
1=
1A
1/
00
b11100110 1
#2310000
1!
0A
10
b11100111 1
#2320000
0$
1#
1"
1(
14
0'
08
0&
0<
0!
02
03
15
16
17
1:
1;
1A
1-
0.
0/
00
b11101000 1
#2330000
1!
0A
10
b11101001 1
#2340000
0"
1&
1<
0!
0:
0;
1=
1A
1/
00
b11101010 1
#2350000
1!
0A
10
b11101011 1
#2360000
0#
1"
1'
18
0&
0<
0!
06
07
19
1:
1;
1A
1.
0/
00
b11101100 1
#2370000
1!
0A
10
b11101101 1
#2380000
0"
1&
1<
0!
0:
0;
1=
1A
1/
00
b11101110 1
#2390000
1!
0A
10
b11101111 1
#2400000
1$
1#
1"
0(
04
0'
08
0&
0<
0@
12
13
16
17
1:
1;
1A
1,
0-
0.
0/
00
b11110000 1
#2410000
0!
1%
1@
0>
0?
1A
10
b11110001 1
#2420000
0"
1!
1&
1<
0%
0@
0:
0;
1=
1>
1?
1/
00
b11110010 1
#2430000
0!
1%
1@
0>
0?
1A
10
b11110011 1
#2440000
0#
1"
1!
1'
18
0&
0<
0%
0@
06
07
19
1:
1;
1>
1?
1.
0/
00
b11110100 1
#2450000
0!
1%
1@
0>
0?
1A
10
b11110101 1
#2460000
0"
1!
1&
1<
0%
0@
0:
0;
1=
1>
1?
1/
00
b11110110 1
#2470000
0!
1%
1@
0>
0?
1A
10
b11110111 1
#2480000
0$
1#
1"
1!
1(
14
0'
08
0&
0<
0%
0@
02
03
15
16
17
1:
1;
1>
1?
1-
0.
0/
00
b11111000 1
#2490000
0!
1%
1@
0>
0?
1A
10
b11111001 1
#2500000
0"
1!
1&
1<
0%
0@
0:
0;
1=
1>
1?
1/
00
b11111010 1
#2510000
0!
1%
1@
0>
0?
1A
10
b11111011 1
#2520000
0#
1"
1!
1'
18
0&
0<
0%
0@
06
07
19
1:
1;
1>
1?
1.
0/
00
b11111100 1
#2530000
0!
1%
1@
0>
0?
1A
10
b11111101 1
#2540000
0"
1!
1&
1<
0%
0@
0:
0;
1=
1>
1?
1/
00
b11111110 1
#2550000
0!
1%
1@
0>
0?
1A
10
b11111111 1
#2560000
b100000000 1
